sparse_autoencoder/__init__.py
sparse_autoencoder/activation_resampler/__init__.py
sparse_autoencoder/activation_resampler/activation_resampler.py
sparse_autoencoder/activation_resampler/tests/test_activation_resampler.py
sparse_autoencoder/activation_resampler/utils/__init__.py
sparse_autoencoder/activation_resampler/utils/component_slice_tensor.py
sparse_autoencoder/activation_store/__init__.py
sparse_autoencoder/activation_store/base_store.py
sparse_autoencoder/activation_store/tensor_store.py
sparse_autoencoder/activation_store/tests/test_tensor_store.py
sparse_autoencoder/autoencoder/__init__.py
sparse_autoencoder/autoencoder/components/__init__.py
sparse_autoencoder/autoencoder/components/linear_encoder.py
sparse_autoencoder/autoencoder/components/tests/__snapshots__/test_linear_encoder.ambr
sparse_autoencoder/autoencoder/components/tests/test_compare_neel_implementation.py
sparse_autoencoder/autoencoder/components/tests/test_linear_encoder.py
sparse_autoencoder/autoencoder/components/tests/test_tied_bias.py
sparse_autoencoder/autoencoder/components/tests/test_unit_norm_decoder.py
sparse_autoencoder/autoencoder/components/tied_bias.py
sparse_autoencoder/autoencoder/components/unit_norm_decoder.py
sparse_autoencoder/autoencoder/lightning.py
sparse_autoencoder/autoencoder/model.py
sparse_autoencoder/autoencoder/tests/__snapshots__/test_model.ambr
sparse_autoencoder/autoencoder/tests/test_model.py
sparse_autoencoder/autoencoder/types.py
sparse_autoencoder/metrics/__init__.py
sparse_autoencoder/metrics/loss/__init__.py
sparse_autoencoder/metrics/loss/l1_absolute_loss.py
sparse_autoencoder/metrics/loss/l2_reconstruction_loss.py
sparse_autoencoder/metrics/loss/sae_loss.py
sparse_autoencoder/metrics/loss/tests/test_l1_absolute_loss.py
sparse_autoencoder/metrics/loss/tests/test_l2_reconstruction_loss.py
sparse_autoencoder/metrics/loss/tests/test_sae_loss.py
sparse_autoencoder/metrics/train/__init__.py
sparse_autoencoder/metrics/train/capacity.py
sparse_autoencoder_fork1-0.0.3.dist-info/LICENSE
sparse_autoencoder_fork1-0.0.3.dist-info/METADATA
sparse_autoencoder_fork1-0.0.3.dist-info/WHEEL
sparse_autoencoder_fork1-0.0.3.dist-info/entry_points.txt
sparse_autoencoder_fork1-0.0.3.dist-info/RECORD
