Metadata-Version: 2.1
Name: sparse_autoencoder_fork1
Version: 0.0.3
Summary: Sparse Autoencoder for Mechanistic Interpretability
License: MIT
Author: Alan Cooney
Author-email: 41682961+alan-cooney@users.noreply.github.com
Requires-Python: >=3.10,<3.12
Classifier: License :: OSI Approved :: MIT License
Classifier: Programming Language :: Python :: 3
Classifier: Programming Language :: Python :: 3.10
Classifier: Programming Language :: Python :: 3.11
Provides-Extra: deepspeed
Requires-Dist: PyYAML (>=5.4,<8.0)
Requires-Dist: accelerate (>=0.26.1)
Requires-Dist: aiohttp (>=3.9.3)
Requires-Dist: cloudpickle (>=2.2.1)
Requires-Dist: colorama (>=0.4.6)
Requires-Dist: datasets (>=2.16.1)
Requires-Dist: deepspeed (>=0.8.2,<=0.9.3) ; extra == "deepspeed"
Requires-Dist: einops (>=0.7.0)
Requires-Dist: fsspec[http] (>=2023.1.0,<=2023.10.0)
Requires-Dist: huggingface-hub (>=0.19.4)
Requires-Dist: jsonschema (>=4.21.1)
Requires-Dist: lightning (>=2.1.3,<3.0.0)
Requires-Dist: matplotlib (>=3.6.3)
Requires-Dist: mpi4py[deepspeed] (>=3.1.5) ; extra == "deepspeed"
Requires-Dist: networkx (>=3.2.1)
Requires-Dist: numpy (>=1.22.4,<2)
Requires-Dist: packaging (>=20.0,<25.0)
Requires-Dist: pandas (>=2.0.0,<3.0.0)
Requires-Dist: psutil (>=5.9.8)
Requires-Dist: pydantic (>=2.6.0)
Requires-Dist: requests (>=2.31.0)
Requires-Dist: strenum (>=0.4.15)
Requires-Dist: sympy (>=1.12)
Requires-Dist: tokenizers (>=0.15.1)
Requires-Dist: torch (==2.1.2)
Requires-Dist: torchmetrics (==1.3.0.post0)
Requires-Dist: tqdm (>=4.57.0,<6.0)
Requires-Dist: transformers (>=4.37.2)
Requires-Dist: typing-extensions (>=4.0.0,<6.0)
Requires-Dist: wandb (>=0.16.2)
Requires-Dist: zstandard (>=0.22.0)
